LICENSE.txt
MANIFEST.in
README.md
VERSION
setup.cfg
setup.py
./deepracer_track_geometry/__init__.py
./deepracer_track_geometry/constants.py
./deepracer_track_geometry/track_geometry.py
./deepracer_track_geometry/utils.py
./deepracer_track_geometry/routes/2022_summit_speedway.npy
./deepracer_track_geometry/routes/albert.npy
./deepracer_track_geometry/routes/americas.npy
./deepracer_track_geometry/routes/aragon.npy
./deepracer_track_geometry/routes/arctic_open.npy
./deepracer_track_geometry/routes/arctic_pro.npy
./deepracer_track_geometry/routes/austin.npy
./deepracer_track_geometry/routes/belille.npy
./deepracer_track_geometry/routes/bowtie.npy
./deepracer_track_geometry/routes/caesar_gp.npy
./deepracer_track_geometry/routes/caesar_loop.npy
./deepracer_track_geometry/routes/canada.npy
./deepracer_track_geometry/routes/china.npy
./deepracer_track_geometry/routes/dubai_open.npy
./deepracer_track_geometry/routes/dubai_pro.npy
./deepracer_track_geometry/routes/fuji.npy
./deepracer_track_geometry/routes/hampton_open.npy
./deepracer_track_geometry/routes/hampton_pro.npy
./deepracer_track_geometry/routes/jyllandsringen_open.npy
./deepracer_track_geometry/routes/jyllandsringen_pro.npy
./deepracer_track_geometry/routes/las_vegas.npy
./deepracer_track_geometry/routes/lgs_wide.npy
./deepracer_track_geometry/routes/mexico.npy
./deepracer_track_geometry/routes/monaco.npy
./deepracer_track_geometry/routes/monaco_building.npy
./deepracer_track_geometry/routes/morgan_open.npy
./deepracer_track_geometry/routes/morgan_pro.npy
./deepracer_track_geometry/routes/new_york.npy
./deepracer_track_geometry/routes/oval.npy
./deepracer_track_geometry/routes/penbay_open.npy
./deepracer_track_geometry/routes/penbay_pro.npy
./deepracer_track_geometry/routes/red_star_open.npy
./deepracer_track_geometry/routes/red_star_pro.npy
./deepracer_track_geometry/routes/reinvent.npy
./deepracer_track_geometry/routes/reinvent2019.npy
./deepracer_track_geometry/routes/reinvent_wide.npy
deepracer_track_geometry.egg-info/PKG-INFO
deepracer_track_geometry.egg-info/SOURCES.txt
deepracer_track_geometry.egg-info/dependency_links.txt
deepracer_track_geometry.egg-info/requires.txt
deepracer_track_geometry.egg-info/top_level.txt